yopp-0.1.2.dist-info/DESCRIPTION.rst
yopp-0.1.2.dist-info/METADATA
yopp-0.1.2.dist-info/metadata.json
yopp-0.1.2.dist-info/WHEEL
yopp-0.1.2.dist-info/RECORD
yopp-0.1.2.dist-info/top_level.txt
yopp/constants.py
yopp/__init__.py
yopp/element_parser.py
yopp/yaml_parser.py
