Metadata-Version: 2.0
Name: yopp
Version: 0.1.2
Summary: Transforms YAML file to python objects using a custom parser
Home-page: https://github.com/guilhermemaba/yopp
Author: Guilherme Luís Maba
Author-email: guilhermemaba@gmail.com
License: ISCL
Keywords: yopp
Platform: UNKNOWN
Classifier: Development Status :: 2 - Pre-Alpha
Classifier: Intended Audience :: Developers
Classifier: License :: OSI Approved :: ISC License (ISCL)
Classifier: Natural Language :: English
Classifier: Programming Language :: Python :: 2
Classifier: Programming Language :: Python :: 2.6
Classifier: Programming Language :: Python :: 2.7
Classifier: Programming Language :: Python :: 3
Classifier: Programming Language :: Python :: 3.3
Classifier: Programming Language :: Python :: 3.4
